lazysearch/__init__.py
lazysearch/lazysearch.py
lazysearch/simple_pattern.py
LazySearch-1.0rc4.dist-info/LICENSE
LazySearch-1.0rc4.dist-info/METADATA
LazySearch-1.0rc4.dist-info/WHEEL
LazySearch-1.0rc4.dist-info/entry_points.txt
LazySearch-1.0rc4.dist-info/top_level.txt
LazySearch-1.0rc4.dist-info/RECORD
